{"cameraMode":{"drawMode":0,"name":"Shaded","section":"Shading Mode"},"sceneLighting":true,"audioPlay":false,"sceneViewState":{"m_AlwaysRefresh":false,"showFog":true,"showSkybox":true,"showFlares":true,"showImageEffects":true,"showParticleSystems":true,"showVisualEffectGraphs":true,"m_FxEnabled":true},"in2DMode":false,"pivot":{"x":1.5722014904022217,"y":1.215423822402954,"z":2.315134286880493},"rotation":{"x":0.03860895708203316,"y":-0.9550427794456482,"z":0.1431521624326706,"w":0.25690343976020815},"size":0.37169796228408816,"orthographic":false}